tronwebpy/__init__.py
tronwebpy/main.py
tronwebpy-0.0.1.dist-info/LICENSE.txt
tronwebpy-0.0.1.dist-info/METADATA
tronwebpy-0.0.1.dist-info/WHEEL
tronwebpy-0.0.1.dist-info/top_level.txt
tronwebpy-0.0.1.dist-info/RECORD
