Metadata-Version: 2.1
Name: tronwebpy
Version: 0.0.1
Summary: Tronweb library for Python
Author: paveltron
Author-email: sanimw3@gmail.com
License: MIT
Project-URL: Source Repository, https://github.com/dcnstrn/tronwebpy
License-File: LICENSE.txt
Requires-Dist: requests
